gshell/__init__.py
gshell.py-0.0.4.dist-info/COPYING
gshell.py-0.0.4.dist-info/METADATA
gshell.py-0.0.4.dist-info/WHEEL
gshell.py-0.0.4.dist-info/top_level.txt
gshell.py-0.0.4.dist-info/RECORD
